braket/analog_hamiltonian_simulator/rydberg/constants.py
braket/analog_hamiltonian_simulator/rydberg/numpy_solver.py
braket/analog_hamiltonian_simulator/rydberg/rydberg_simulator.py
braket/analog_hamiltonian_simulator/rydberg/rydberg_simulator_helpers.py
braket/analog_hamiltonian_simulator/rydberg/rydberg_simulator_result_converter.py
braket/analog_hamiltonian_simulator/rydberg/rydberg_simulator_unit_converter.py
braket/analog_hamiltonian_simulator/rydberg/scipy_solver.py
braket/analog_hamiltonian_simulator/rydberg/validators/atom_arrangement.py
braket/analog_hamiltonian_simulator/rydberg/validators/blockade_radius.py
braket/analog_hamiltonian_simulator/rydberg/validators/capabilities_constants.py
braket/analog_hamiltonian_simulator/rydberg/validators/driving_field.py
braket/analog_hamiltonian_simulator/rydberg/validators/field_validator_util.py
braket/analog_hamiltonian_simulator/rydberg/validators/hamiltonian.py
braket/analog_hamiltonian_simulator/rydberg/validators/ir_validator.py
braket/analog_hamiltonian_simulator/rydberg/validators/physical_field.py
braket/analog_hamiltonian_simulator/rydberg/validators/program.py
braket/analog_hamiltonian_simulator/rydberg/validators/rydberg_coefficient.py
braket/analog_hamiltonian_simulator/rydberg/validators/shifting_field.py
braket/analog_hamiltonian_simulator/rydberg/validators/times_series.py
braket/default_simulator/__init__.py
braket/default_simulator/_version.py
braket/default_simulator/density_matrix_simulation.py
braket/default_simulator/density_matrix_simulator.py
braket/default_simulator/gate_operations.py
braket/default_simulator/linalg_utils.py
braket/default_simulator/noise_operations.py
braket/default_simulator/observables.py
braket/default_simulator/operation.py
braket/default_simulator/operation_helpers.py
braket/default_simulator/result_types.py
braket/default_simulator/simulation.py
braket/default_simulator/simulator.py
braket/default_simulator/state_vector_simulation.py
amazon_braket_default_simulator_kshitijc-1.11.2.dev0.dist-info/LICENSE
amazon_braket_default_simulator_kshitijc-1.11.2.dev0.dist-info/METADATA
amazon_braket_default_simulator_kshitijc-1.11.2.dev0.dist-info/NOTICE
amazon_braket_default_simulator_kshitijc-1.11.2.dev0.dist-info/WHEEL
amazon_braket_default_simulator_kshitijc-1.11.2.dev0.dist-info/entry_points.txt
amazon_braket_default_simulator_kshitijc-1.11.2.dev0.dist-info/top_level.txt
amazon_braket_default_simulator_kshitijc-1.11.2.dev0.dist-info/RECORD
