Metadata-Version: 2.1
Name: amazon-braket-default-simulator-kshitijc
Version: 1.11.2.dev0
Summary: An open source quantum circuit simulator to be run locally with the Amazon Braket SDK
Home-page: https://github.com/aws/amazon-braket-default-simulator-python
Author: Amazon Web Services
License: Apache License 2.0
Keywords: Amazon AWS Quantum
Classifier: Development Status :: 5 - Production/Stable
Classifier: Intended Audience :: Developers
Classifier: Natural Language :: English
Classifier: License :: OSI Approved :: Apache Software License
Classifier: Programming Language :: Python
Classifier: Programming Language :: Python :: 3.7
Classifier: Programming Language :: Python :: 3.8
Classifier: Programming Language :: Python :: 3.9
Requires-Python: >= 3.7
License-File: LICENSE
License-File: NOTICE
Requires-Dist: numpy
Requires-Dist: opt-einsum
Requires-Dist: pydantic (<2.0,>=1.9)
Requires-Dist: scipy
Requires-Dist: antlr4-python3-runtime (==4.11.1)
Requires-Dist: amazon-braket-schemas (>=1.12.0)
Provides-Extra: test
Requires-Dist: black ; extra == 'test'
Requires-Dist: coverage ; extra == 'test'
Requires-Dist: flake8 ; extra == 'test'
Requires-Dist: isort ; extra == 'test'
Requires-Dist: pre-commit ; extra == 'test'
Requires-Dist: pylint ; extra == 'test'
Requires-Dist: pytest (==7.1.2) ; extra == 'test'
Requires-Dist: pytest-benchmark ; extra == 'test'
Requires-Dist: pytest-cov ; extra == 'test'
Requires-Dist: pytest-rerunfailures ; extra == 'test'
Requires-Dist: pytest-xdist ; extra == 'test'
Requires-Dist: sphinx ; extra == 'test'
Requires-Dist: sphinx-rtd-theme ; extra == 'test'
Requires-Dist: sphinxcontrib-apidoc ; extra == 'test'
Requires-Dist: tox ; extra == 'test'
